psifr/__init__.py
psifr/fr.py
psifr/maskers.py
psifr/measures.py
psifr/stats.py
psifr/data/Morton2013.csv
psifr/data/peers_notask.csv
psifr/distances/Morton2013.npz
psifr-0.10.1.dist-info/licenses/LICENSE
psifr-0.10.1.dist-info/METADATA
psifr-0.10.1.dist-info/WHEEL
psifr-0.10.1.dist-info/top_level.txt
psifr-0.10.1.dist-info/RECORD
