Metadata-Version: 2.4
Name: psifr
Version: 0.10.1
Summary: Psifr: Analysis and visualization of free recall data
Author-email: Neal W Morton <mortonne@gmail.com>
License: GPL-3.0-or-later
Keywords: psychology,memory,free recall
Classifier: Programming Language :: Python :: 3
Classifier: License :: OSI Approved :: GNU General Public License v3 or later (GPLv3+)
Classifier: Operating System :: OS Independent
Requires-Python: >=3.8
License-File: LICENSE
Requires-Dist: numpy
Requires-Dist: scipy
Requires-Dist: pandas>=1.0.0
Requires-Dist: matplotlib!=3.3.1
Requires-Dist: seaborn>=0.9.3
Provides-Extra: docs
Requires-Dist: sphinx; extra == "docs"
Requires-Dist: pydata-sphinx-theme; extra == "docs"
Requires-Dist: ipython; extra == "docs"
Requires-Dist: sphinxcontrib-bibtex; extra == "docs"
Requires-Dist: pickleshare; extra == "docs"
Provides-Extra: test
Requires-Dist: pytest; extra == "test"
Requires-Dist: codecov; extra == "test"
Requires-Dist: pytest-cov; extra == "test"
Provides-Extra: perf
Requires-Dist: snakeviz; extra == "perf"
Requires-Dist: asv; extra == "perf"
Dynamic: license-file
